citrosNavigationCalc/__init__.py
citrosNavigationCalc/navigation_error_class.py
citrosNavigationCalc/navigation_error_plot_class.py
citrosNavigationCalc-0.0.12.dist-info/METADATA
citrosNavigationCalc-0.0.12.dist-info/WHEEL
citrosNavigationCalc-0.0.12.dist-info/top_level.txt
citrosNavigationCalc-0.0.12.dist-info/RECORD
