Metadata-Version: 2.1
Name: citrosNavigationCalc
Version: 0.0.12
Summary: A navigation calculator that is compatible with the CITROS Data Analysis package
Home-page: UNKNOWN
Author: Boaz Gavriel
Author-email: <boaz@lulav.space>
License: UNKNOWN
Keywords: python,first package
Platform: UNKNOWN
Classifier: Development Status :: 3 - Alpha
Classifier: Intended Audience :: Education
Classifier: Programming Language :: Python :: 3
Classifier: Operating System :: MacOS :: MacOS X
Classifier: Operating System :: Microsoft :: Windows
Requires-Dist: citros-data-analysis
Requires-Dist: matplotlib
Requires-Dist: numpy
Requires-Dist: pandas
